pyterraform/__init__.py
pyterraform/__main__.py
pyterraform/cli_tools.py
pyterraform/constants.py
pyterraform/inputs.py
pyterraform/logs.py
pyterraform/paths.py
pyterraform/project.py
pyterraform/session.py
pyterraform/utils.py
pyterraform/config/__init__.py
pyterraform/config/setup.py
pyterraform/terraform/__init__.py
pyterraform/terraform/binaries.py
pyterraform-0.0.1.dist-info/LICENSE
pyterraform-0.0.1.dist-info/METADATA
pyterraform-0.0.1.dist-info/WHEEL
pyterraform-0.0.1.dist-info/top_level.txt
pyterraform-0.0.1.dist-info/RECORD
